{
    "classifier": "xgb",
    "selector": "mrmr",
    "feature_aggregation": "3largest",
    "average_auc": 0.7205392156862744,
    "std_dev_auc": 0.03209804382962682,
    "hyperparameters": {
        "n_estimators": 100,
        "learning_rate": 0.2,
        "max_depth": 5,
        "subsample": 0.8
    },
    "features": [
        "original_shape_Flatness",
        "n_lesions",
        "original_glrlm_ShortRunEmphasis",
        "original_glszm_SizeZoneNonUniformityNormalized",
        "baseline_num_met_organs"
    ],
    "feature_importances": {
        "original_shape_Flatness": 0.20976565778255463,
        "n_lesions": 0.2663978636264801,
        "original_glrlm_ShortRunEmphasis": 0.18988648056983948,
        "original_glszm_SizeZoneNonUniformityNormalized": 0.18600527942180634,
        "baseline_num_met_organs": 0.14794476330280304
    }
}